dcov/__init__.py
dcov/command_runner.py
dcov/config_parser.py
dcov/diff_cover_tool.py
dcov/diff_quality_tool.py
dcov/diff_reporter.py
dcov/git_diff.py
dcov/git_path.py
dcov/hook.py
dcov/hookspecs.py
dcov/report_generator.py
dcov/snippets.py
dcov/templates/console_coverage_report.txt
dcov/templates/console_quality_report.txt
dcov/templates/external_style.css
dcov/templates/html_coverage_report.html
dcov/templates/html_quality_report.html
dcov/templates/markdown_coverage_report.md
dcov/templates/markdown_quality_report.md
dcov/templates/snippet_content.html
dcov/templates/snippet_content.md
dcov/templates/snippet_content.txt
dcov/templates/snippet_style.html
dcov/util.py
dcov/violationsreporters/__init__.py
dcov/violationsreporters/base.py
dcov/violationsreporters/java_violations_reporter.py
dcov/violationsreporters/violations_reporter.py
dcov-1.0.12.dist-info/entry_points.txt
dcov-1.0.12.dist-info/LICENSE
dcov-1.0.12.dist-info/WHEEL
dcov-1.0.12.dist-info/METADATA
dcov-1.0.12.dist-info/RECORD
